{
  "7.27.21": {
    "festivals": "Gauri Vrat"
  },
  "7.28.21": {
    "festivals": "None"
  },
  "7.29.21": {
    "festivals": "None"
  },
  "7.30.21": {
    "festivals": "Kalashtami"
  },

  "8.1.21": {
    "festivals": "Friendship Day"
  },
  "8.2.21": {
    "festivals": "None"
  },
  "8.3.21": {
    "festivals": "Gauri Vrat"
  },
  "8.4.21": {
    "festivals": "Kamika Ekadashi"
  },
  "8.5.21": {
    "festivals": "Pradosh Vrat"
  },
  "8.6.21": {
    "festivals": "Masik Shivaratri"
  },
  "8.7.21": {
    "festivals": "Amavasya"
  },
  "8.8.21": {
    "festivals": "Ishti"
  },
  "8.9.21": {
    "festivals": "Chandra Darshana"
  },
  "8.10.21": {
    "festivals": "Andal Jayanthi"
  },
  "8.11.21": {
    "festivals": "Vinayaka Chaturthi"
  },
  "8.12.21": {
    "festivals": "Nag Panchami"
  },
  "8.13.21": {
    "festivals": "Kalki Jayanti"
  },
  "8.14.21": {
    "festivals": "Tulsidas Jayanti"
  },
  "8.15.21": {
    "festivals": "India Independence Day"
  },
  "8.16.21": {
    "festivals": "None"
  },
  "8.17.21": {
    "festivals": "Malayalam New Year"
  },
  "8.18.21": {
    "festivals": "Damodara Dwadashi"
  },
  "8.19.21": {
    "festivals": "Pradosh Vrat"
  },
  "8.20.21": {
    "festivals": "Varalakshmi Vrat"
  },
  "8.21.21": {
    "festivals": "Onam"
  },
  "8.22.21": {
    "festivals": "Raksha Bandhan"
  },
  "8.23.21": {
    "festivals": "None"
  },
  "8.24.21": {
    "festivals": "None"
  },
  "8.25.21": {
    "festivals": "None"
  },
  "8.26.21": {
    "festivals": "None"
  },
  "8.27.21": {
    "festivals": "None"
  },
  "8.28.21": {
    "festivals": "Balarama Jayanti"
  },
  "8.29.21": {
    "festivals": "Kali Jayanti"
  },
  "8.30.21": {
    "festivals": "None"
  },
  "8.31.21": {
    "festivals": "None"
  },

  "9.1.21": {
    "festivals": "None"
  },
  "9.2.21": {
    "festivals": "Aja Ekadashi"
  },
  "9.3.21": {
    "festivals": "None"
  },
  "9.4.21": {
    "festivals": "Pradosh Vrat"
  },
  "9.5.21": {
    "festivals": "None"
  },
  "9.6.21": {
    "festivals": "None"
  },
  "9.7.21": {
    "festivals": "Ishti"
  },
  "9.8.21": {
    "festivals": "Varaha Jayanti"
  },
  "9.9.21": {
    "festivals": "Gowri Habba"
  },
  "9.10.21": {
    "festivals": "Ganesh Chaturthi"
  },
  "9.11.21": {
    "festivals": "None"
  },
  "9.12.21": {
    "festivals": "None"
  },
  "9.13.21": {
    "festivals": "None"
  },
  "9.14.21": {
    "festivals": "None"
  },
  "9.15.21": {
    "festivals": "None"
  },
  "9.16.21": {
    "festivals": "Vishwakarma Puja"
  },
  "9.17.21": {
    "festivals": "Vamana Jayanti"
  },
  "9.18.21": {
    "festivals": "Pradosh Vrat"
  },
  "9.19.21": {
    "festivals": "None"
  },
  "9.20.21": {
    "festivals": "Purnima"
  },
  "9.21.21": {
    "festivals": "None"
  },
  "9.22.21": {
    "festivals": "None"
  },
  "9.23.21": {
    "festivals": "None"
  },
  "9.24.21": {
    "festivals": "None"
  },
  "9.25.21": {
    "festivals": "None"
  },
  "9.26.21": {
    "festivals": "None"
  },
  "9.27.21": {
    "festivals": "None"
  },
  "9.28.21": {
    "festivals": "None"
  },
  "9.29.21": {
    "festivals": "None"
  },
  "9.30.21": {
    "festivals": "None"
  },
 
  "10.1.21": {
    "festivals": "None"
  },
  "10.2.21": {
    "festivals": "Gandhi Jayanti"
  },
  "10.3.21": {
    "festivals": "None"
  },
  "10.4.21": {
    "festivals": "None"
  },
  "10.5.21": {
    "festivals": "Navratri Begins Tomorrow"
  },
  "10.6.21": {
    "festivals": "Navratri Day 1"
  },
  "10.7.21": {
    "festivals": "Navratri Day 2"
  },
  "10.8.21": {
    "festivals": "Navratri Day 3"
  },
  "10.9.21": {
    "festivals": "Navratri Day 4"
  },
  "10.10.21": {
    "festivals": "Navratri Day 5"
  },
  "10.11.21": {
    "festivals": "Navratri Day 6"
  },
  "10.12.21": {
    "festivals": "Navratri Day 7"
  },
  "10.13.21": {
    "festivals": "Navratri Day 8"
  },
  "10.14.21": {
    "festivals": "Dussehra"
  },
  "10.15.21": {
    "festivals": "None"
  },
  "10.16.21": {
    "festivals": "None"
  },
  "10.17.21": {
    "festivals": "Pradosh Vrat"
  },
  "10.18.21": {
    "festivals": "None"
  },
  "10.19.21": {
    "festivals": "None"
  },
  "10.20.21": {
    "festivals": "Valmiki Jayanti"
  },
  "10.21.21": {
    "festivals": "None"
  },
  "10.22.21": {
    "festivals": "None"
  },
  "10.23.21": {
    "festivals": "None"
  },
  "10.24.21": {
    "festivals": "None"
  },
  "10.25.21": {
    "festivals": "None"
  },
  "10.26.21": {
    "festivals": "None"
  },
  "10.27.21": {
    "festivals": "None"
  },
  "10.28.21": {
    "festivals": "None"
  },
  "10.29.21": {
    "festivals": "None"
  },
  "10.30.21": {
    "festivals": "None"
  },
  "10.31.21": {
    "festivals": "None"
  }



  
  }